CHANGELOG.md
LICENSE.txt
MANIFEST.in
README.md
setup.py
PyMulti/__init__.py
PyMulti.egg-info/PKG-INFO
PyMulti.egg-info/SOURCES.txt
PyMulti.egg-info/dependency_links.txt
PyMulti.egg-info/requires.txt
PyMulti.egg-info/top_level.txt
PyMulti/English/Grammar.py
PyMulti/English/Words.py
PyMulti/English/__init__.py
PyMulti/English/assets/dictionary.json
PyMulti/Files/JSON.py
PyMulti/Files/__init__.py
PyMulti/Fun/__init__.py
PyMulti/JokesFacts/__init__.py
PyMulti/Math/Algebra.py
PyMulti/Math/Arithmetic.py
PyMulti/Math/Geometry.py
PyMulti/Math/Graphs.py
PyMulti/Math/Statistics.py
PyMulti/Math/Trigonometry.py
PyMulti/Math/__init__.py
PyMulti/Speech/TextToSpeech.py
PyMulti/Speech/__init__.py
PyMulti/System/Brightness.py
PyMulti/System/Clipboard.py
PyMulti/System/MessageBox.py
PyMulti/System/Volume.py
PyMulti/System/__init__.py
PyMulti/System/assets/SetVol.exe
PyMulti/Traffic/LicensePlate.py
PyMulti/Traffic/PeopleDetection.py
PyMulti/Traffic/VehicleDetection.py
PyMulti/Traffic/__init__.py
PyMulti/Traffic/assets/models/haarcascade_car.xml
PyMulti/Traffic/assets/models/haarcascade_russian_plate_number.xml
PyMulti/Traffic/assets/sample_media/LicensePlate/images/1.jpg
PyMulti/Traffic/assets/sample_media/LicensePlate/images/2.jpg
PyMulti/Traffic/assets/sample_media/LicensePlate/images/3.jpg
PyMulti/Traffic/assets/sample_media/LicensePlate/images/4.jpg
PyMulti/Traffic/assets/sample_media/LicensePlate/images/5.jpg
PyMulti/Traffic/assets/sample_media/LicensePlate/images/6.jpg
PyMulti/Traffic/assets/sample_media/LicensePlate/images/7.jpg
PyMulti/Traffic/assets/sample_media/LicensePlate/images/8.jpg
PyMulti/Traffic/assets/sample_media/PeopleDetection/videos/1.mp4
PyMulti/Traffic/assets/sample_media/PeopleDetection/videos/2.mp4
PyMulti/Traffic/assets/sample_media/PeopleDetection/videos/3.mp4
PyMulti/Traffic/assets/sample_media/PeopleDetection/videos/4.mp4
PyMulti/Traffic/assets/sample_media/PeopleDetection/videos/5.mp4
PyMulti/Traffic/assets/sample_media/VehicleDetection/images/1.jpg
PyMulti/Traffic/assets/sample_media/VehicleDetection/images/10.jpg
PyMulti/Traffic/assets/sample_media/VehicleDetection/images/2.jpg
